ansys/api/fluent/__init__.py
ansys/api/fluent/_version.py
ansys/api/fluent/py.typed
ansys/api/fluent/v0/Connection_pb2.py
ansys/api/fluent/v0/Connection_pb2.pyi
ansys/api/fluent/v0/Connection_pb2_grpc.py
ansys/api/fluent/v0/Connection_pb2_grpc.pyi
ansys/api/fluent/v0/app_utilities_pb2.py
ansys/api/fluent/v0/app_utilities_pb2.pyi
ansys/api/fluent/v0/app_utilities_pb2_grpc.py
ansys/api/fluent/v0/app_utilities_pb2_grpc.pyi
ansys/api/fluent/v0/batch_ops_pb2.py
ansys/api/fluent/v0/batch_ops_pb2.pyi
ansys/api/fluent/v0/batch_ops_pb2_grpc.py
ansys/api/fluent/v0/batch_ops_pb2_grpc.pyi
ansys/api/fluent/v0/common_api_pb2.py
ansys/api/fluent/v0/common_api_pb2.pyi
ansys/api/fluent/v0/common_api_pb2_grpc.py
ansys/api/fluent/v0/common_api_pb2_grpc.pyi
ansys/api/fluent/v0/common_pb2.py
ansys/api/fluent/v0/common_pb2.pyi
ansys/api/fluent/v0/common_pb2_grpc.py
ansys/api/fluent/v0/common_pb2_grpc.pyi
ansys/api/fluent/v0/datamodel_se_pb2.py
ansys/api/fluent/v0/datamodel_se_pb2.pyi
ansys/api/fluent/v0/datamodel_se_pb2_grpc.py
ansys/api/fluent/v0/datamodel_se_pb2_grpc.pyi
ansys/api/fluent/v0/datamodel_tui_pb2.py
ansys/api/fluent/v0/datamodel_tui_pb2.pyi
ansys/api/fluent/v0/datamodel_tui_pb2_grpc.py
ansys/api/fluent/v0/datamodel_tui_pb2_grpc.pyi
ansys/api/fluent/v0/events_pb2.py
ansys/api/fluent/v0/events_pb2.pyi
ansys/api/fluent/v0/events_pb2_grpc.py
ansys/api/fluent/v0/events_pb2_grpc.pyi
ansys/api/fluent/v0/field_data_pb2.py
ansys/api/fluent/v0/field_data_pb2.pyi
ansys/api/fluent/v0/field_data_pb2_grpc.py
ansys/api/fluent/v0/field_data_pb2_grpc.pyi
ansys/api/fluent/v0/health_pb2.py
ansys/api/fluent/v0/health_pb2.pyi
ansys/api/fluent/v0/health_pb2_grpc.py
ansys/api/fluent/v0/health_pb2_grpc.pyi
ansys/api/fluent/v0/meshing_queries_pb2.py
ansys/api/fluent/v0/meshing_queries_pb2.pyi
ansys/api/fluent/v0/meshing_queries_pb2_grpc.py
ansys/api/fluent/v0/meshing_queries_pb2_grpc.pyi
ansys/api/fluent/v0/monitor_pb2.py
ansys/api/fluent/v0/monitor_pb2.pyi
ansys/api/fluent/v0/monitor_pb2_grpc.py
ansys_api_fluent-0.3.36.dist-info/licenses/LICENSE
ansys_api_fluent-0.3.36.dist-info/METADATA
ansys_api_fluent-0.3.36.dist-info/WHEEL
ansys_api_fluent-0.3.36.dist-info/entry_points.txt
ansys_api_fluent-0.3.36.dist-info/top_level.txt
ansys_api_fluent-0.3.36.dist-info/RECORD
