Metadata-Version: 2.4
Name: ansys-api-fluent
Version: 0.3.36
Summary: Autogenerated python gRPC interface package for ansys-api-fluent, built on 11:48:30 on 20 June 2025
Author: ANSYS, Inc.
Author-email: support@ansys.com
License: MIT
Requires-Python: >=3.7
License-File: LICENSE
Requires-Dist: grpcio~=1.30
Requires-Dist: protobuf<5,>=3.19
Dynamic: author
Dynamic: author-email
Dynamic: description
Dynamic: description-content-type
Dynamic: license
Dynamic: license-file
Dynamic: requires-dist
Dynamic: requires-python
Dynamic: summary
